4 bit SISO register/design.sv
module siso_register (
  input wire serial_in, // Serial input
  input wire clock, // Clock input
  input wire shift, // Shift control input
  output reg serial_out // Serial output
);

  reg [3:0] shift_reg;

  always @(posedge clock) begin
    if (shift) begin
      shift_reg <= {shift_reg[2:0], serial_in};
    end
  end

  always @(posedge clock) begin
    serial_out <= shift_reg[3];
  end

endmodule

4 bit SISO register/testbench.sv
module tb_siso_register;

  reg serial_in;
  reg clock;
  reg shift;
  wire serial_out;

  siso_register uut (
    .serial_in(serial_in),
    .clock(clock),
    .shift(shift),
    .serial_out(serial_out)
  );

  initial begin
    // Open VCD file for waveform dumping
    $dumpfile("waveform.vcd");
    $dumpvars(0, tb_siso_register); // Dump all variables
    
    // Initialize inputs
    serial_in = 1;
    clock = 0;
    shift = 0;
    
    // Apply inputs and check outputs
    #5 shift = 1; // Shift data
    #5 shift = 0;
    serial_in = 0; // Change serial_in
    #5 shift = 1; // Shift data
    #5 shift = 0;
    serial_in = 1; // Change serial_in
    #5 shift = 1; // Shift data
    
    // Clock toggling
    repeat (10) begin
      #5 clock = ~clock;
    end
    
    // Finish simulation
    $finish;
  end

endmodule

4 bit SISO register/waveform.vcd
$date
	Wed Oct 11 05:41:29 2023
$end
$version
	Icarus Verilog
$end
$timescale
	1s
$end
$scope module tb_siso_register $end
$var wire 1 ! serial_out $end
$var reg 1 " clock $end
$var reg 1 # serial_in $end
$var reg 1 $ shift $end
$scope module uut $end
$var wire 1 % clock $end
$var wire 1 & serial_in $end
$var wire 1 ' shift $end
$var reg 1 ( serial_out $end
$var reg 4 ) shift_reg [3:0] $end
$upscope $end
$upscope $end
$enddefinitions $end
#0
$dumpvars
bx )
x(
0'
1&
0%
0$
1#
0"
x!
$end
#5
1$
1'
#10
0#
0&
0$
0'
#15
1$
1'
#20
1#
1&
0$
0'
#25
1$
1'
#30
bx1 )
1"
1%
#35
0"
0%
#40
bx11 )
1"
1%
#45
0"
0%
#50
bx111 )
1"
1%
#55
0"
0%
#60
b1111 )
1"
1%
#65
0"
0%
#70
1(
1!
1"
1%
