Johnson Counter/design.sv
module johnson_counter (
  input wire clk, // Clock input
  input wire reset, // Reset input
  output reg [3:0] count // 4-bit counter output
);

  always @(posedge clk or posedge reset) begin
    if (reset) begin
      count <= 4'b0001;
    end else begin
      count <= {count[2:0], ~count[3]};
    end
  end

endmodule

Johnson Counter/testbench.sv
module testbench;

  reg clk;
  reg reset;
  wire [3:0] count;

  johnson_counter uut (
    .clk(clk),
    .reset(reset),
    .count(count)
  );

  initial begin
    // Open VCD file for waveform dumping
    $dumpfile("waveform.vcd");
    $dumpvars(0, testbench); // Dump all variables
    
    // Initialize inputs
    clk = 0;
    reset = 0;
    
    // Apply inputs and check outputs
    #5 reset = 1;
    #5 reset = 0;
    #10 clk = 1; #5 clk = 0; // Shift counter (0001 -> 1000)
    #10 clk = 1; #5 clk = 0; // Shift counter (1000 -> 1100)
    #10 clk = 1; #5 clk = 0; // Shift counter (1100 -> 1110)
    #10 clk = 1; #5 clk = 0; // Shift counter (1110 -> 1111)
    #10 clk = 1; #5 clk = 0; // Shift counter (1111 -> 0111)
    #10 clk = 1; #5 clk = 0; // Shift counter (0111 -> 0011)
    #10 clk = 1; #5 clk = 0; // Shift counter (0011 -> 0001)
    #10 clk = 1; #5 clk = 0; // Shift counter (0001 -> 1000)
    
    // Finish simulation
    $finish;
  end

endmodule

Johnson Counter/waveform.vcd
$date
	Sun Sep 24 03:28:19 2023
$end
$version
	Icarus Verilog
$end
$timescale
	1s
$end
$scope module testbench $end
$var wire 4 ! count [3:0] $end
$var reg 1 " clk $end
$var reg 1 # reset $end
$scope module uut $end
$var wire 1 $ clk $end
$var wire 1 % reset $end
$var reg 4 & count [3:0] $end
$upscope $end
$upscope $end
$enddefinitions $end
#0
$dumpvars
bx &
0%
0$
0#
0"
bx !
$end
#5
b1 &
b1 !
1#
1%
#10
0#
0%
#20
b11 &
b11 !
1"
1$
#25
0"
0$
#35
b111 &
b111 !
1"
1$
#40
0"
0$
#50
b1111 &
b1111 !
1"
1$
#55
0"
0$
#65
b1110 &
b1110 !
1"
1$
#70
0"
0$
#80
b1100 &
b1100 !
1"
1$
#85
0"
0$
#95
b1000 &
b1000 !
1"
1$
#100
0"
0$
#110
b0 &
b0 !
1"
1$
#115
0"
0$
#125
b1 &
b1 !
1"
1$
