1:4 Demultiplexer/design.sv
module demux_1_4(
  input [1:0] sel,
  input  i,
  output reg y0,y1,y2,y3);
    
  always @(*) begin
    case(sel)
      2'h0: {y0,y1,y2,y3} = {i,3'b0};
      2'h1: {y0,y1,y2,y3} = {1'b0,i,2'b0};
      2'h2: {y0,y1,y2,y3} = {2'b0,i,1'b0};
      2'h3: {y0,y1,y2,y3} = {3'b0,i};
      default: $display("Invalid sel input");
    endcase
  end
endmodule

1:4 Demultiplexer/testbench.sv
module tb;
  reg [1:0] sel;
  reg i;
  wire y0,y1,y2,y3;
  
  demux_1_4 demux(sel, i, y0, y1, y2, y3);
  
  initial begin
    $monitor("sel = %b, i = %b -> y0 = %0b, y1 = %0b ,y2 = %0b, y3 = %0b", sel,i, y0,y1,y2,y3);
    $dumpfile("dump.vcd");
    $dumpvars(1);
    sel=2'b00; i=0; #1;
    sel=2'b00; i=1; #1;
    sel=2'b01; i=0; #1;
    sel=2'b01; i=1; #1;
    sel=2'b10; i=0; #1;
    sel=2'b10; i=1; #1;
    sel=2'b11; i=0; #1;
    sel=2'b11; i=1; #1;
  end
endmodule

1:4 Demultiplexer/dump.vcd
$date
	Tue Aug 15 04:22:00 2023
$end
$version
	Icarus Verilog
$end
$timescale
	1s
$end
$scope module tb $end
$var wire 1 ! y0 $end
$var wire 1 " y1 $end
$var wire 1 # y2 $end
$var wire 1 $ y3 $end
$var reg 1 % i $end
$var reg 2 & sel [1:0] $end
$upscope $end
$enddefinitions $end
#0
$dumpvars
b0 &
0%
0$
0#
0"
0!
$end
#1
1!
1%
#2
0!
0%
b1 &
#3
1"
1%
#4
0"
0%
b10 &
#5
1#
1%
#6
0#
0%
b11 &
#7
1$
1%
