Full Adder/design.sv

module full_adder (
  input wire A, // Input A
  input wire B, // Input B
  input wire Cin, // Carry in
  output reg SUM, // Sum output
  output reg Cout // Carry out
);

  always @(*) begin
    SUM = A ^ B ^ Cin;
    Cout = (A & B) | (B & Cin) | (A & Cin);
  end

endmodule

Full Adder/testbench.sv
module testbench;

  reg A;
  reg B;
  reg Cin;
  wire SUM;
  wire Cout;

  full_adder uut (
    .A(A),
    .B(B),
    .Cin(Cin),
    .SUM(SUM),
    .Cout(Cout)
  );

  initial begin
    // Open VCD file for waveform dumping
    $dumpfile("waveform.vcd");
    $dumpvars(0, testbench); // Dump all variables
    
    // Initialize inputs
    A = 1'b0;
    B = 1'b0;
    Cin = 1'b0;
    
    // Apply inputs and check outputs
    #5 A = 1'b0; B = 1'b1; Cin = 1'b0;
    #5 A = 1'b1; B = 1'b0; Cin = 1'b0;
    #5 A = 1'b1; B = 1'b1; Cin = 1'b0;
    #5 A = 1'b0; B = 1'b0; Cin = 1'b1;
    #5 A = 1'b0; B = 1'b1; Cin = 1'b1;
    #5 A = 1'b1; B = 1'b0; Cin = 1'b1;
    #5 A = 1'b1; B = 1'b1; Cin = 1'b1;
    
    // Finish simulation
    $finish;
  end

endmodule

Full Adder/waveform.vcd
$date
	Sun Sep 17 19:09:49 2023
$end
$version
	Icarus Verilog
$end
$timescale
	1s
$end
$scope module testbench $end
$var wire 1 ! Cout $end
$var wire 1 " SUM $end
$var reg 1 # A $end
$var reg 1 $ B $end
$var reg 1 % Cin $end
$scope module uut $end
$var wire 1 & A $end
$var wire 1 ' B $end
$var wire 1 ( Cin $end
$var reg 1 ) Cout $end
$var reg 1 * SUM $end
$upscope $end
$upscope $end
$enddefinitions $end
#0
$dumpvars
0*
0)
0(
0'
0&
0%
0$
0#
0"
0!
$end
#5
1*
1"
1$
1'
#10
0$
0'
1#
1&
#15
1)
1!
0*
0"
1$
1'
#20
0)
0!
1*
1"
1%
1(
0$
0'
0#
0&
#25
1)
1!
0*
0"
1$
1'
#30
0$
0'
1#
1&
#35
1*
1"
1$
1'
