16:1 Multiplexer/design.sv
`timescale 1ns/100ps
module MULTI(E0,E1,E2,E3,E4,E5,E6,E7,E8,E9,E10,E11,E12,E13,E14,E15,sel0,sel1,sel2,sel3,S,C1,C2);
  input E0,E1,E2,E3,E4,E5,E6,E7,E8,E9,E10,E11,E12,E13,E14,E15;
  input sel0,sel1, sel2, sel3;
  output reg S, C1, C2;
  
//always block begins here
  
  always @(E0,E1,E2,E3,E4,E5,E6,E7,E8,E9,E10,E11,E12,E13,E14,E15,sel0,sel1,sel2,sel3)
    begin
      case({sel0,sel1,sel2})
        3'b000: begin
          C1=E8;
          C2=E0;
        end
        3'b001: begin
          C1=E9;
          C2=E1;
        end
        3'b010: begin
          C1=E10;
          C2=E2;
        end
        3'b011: begin
          C1=E11;
          C2=E3;
        end
        3'b100: begin
          C1=E12;
          C2=E4;
        end
        3'b101: begin
          C1=E13;
          C2=E5;
        end
        3'b110: begin
          C1=E14;
          C2=E6;
        end
        3'b111: begin
          C1=E15; 
          C2=E7;
        end
      endcase
    
      case(sel3)
        1'b0: S=C1;
        1'b1: S=C2;
      endcase
    end
endmodule

16:1 Multiplexer/testbench.sv

`timescale 1ns/100ps

module test_MULTI();
  reg E0,E1,E2,E3,E4,E5,E6,E7,E8,E9,E10,E11,E12,E13,E14,E15,sel0,sel1,sel2,sel3;
  wire S, C1, C2;
  MULTI MULTI(E0,E1,E2,E3,E4,E5,E6,E7,E8,E9,E10,E11,E12,E13,E14,E15,sel0,sel1,sel2,sel3,S,C1,C2);
  initial
    begin
      $dumpfile("out.vcd");
      $dumpvars(1,test_MULTI);
      
//For different time breaks    
  #10 E0 = 1'b0; sel3 = 1'b1; sel0 = 1'b0; sel1 = 1'b0; sel2 = 1'b0;
  #10 E0 = 1'b1; sel3 = 1'b1; sel0 = 1'b0; sel1 = 1'b0; sel2 = 1'b0;
  #10 E1 = 1'b0; sel3 = 1'b1; sel0 = 1'b0; sel1 = 1'b0; sel2 = 1'b1;
  #10 E1 = 1'b1; sel3 = 1'b1; sel0 = 1'b0; sel1 = 1'b0; sel2 = 1'b1;
  #10 E2 = 1'b0; sel3 = 1'b1; sel0 = 1'b0; sel1 = 1'b1; sel2 = 1'b0;
  #10 E2 = 1'b1; sel3 = 1'b1; sel0 = 1'b0; sel1 = 1'b1; sel2 = 1'b0;
  #10 E3 = 1'b0; sel3 = 1'b1; sel0 = 1'b0; sel1 = 1'b1; sel2 = 1'b1;
  #10 E3 = 1'b1; sel3 = 1'b1; sel0 = 1'b0; sel1 = 1'b1; sel2 = 1'b1;
  #10 E4 = 1'b0; sel3 = 1'b1; sel0 = 1'b1; sel1 = 1'b0; sel2 = 1'b0;
  #10 E4 = 1'b1; sel3 = 1'b1; sel0 = 1'b1; sel1 = 1'b0; sel2 = 1'b0;
  #10 E5 = 1'b0; sel3 = 1'b1; sel0 = 1'b1; sel1 = 1'b0; sel2 = 1'b1;
  #10 E5 = 1'b1; sel3 = 1'b1; sel0 = 1'b1; sel1 = 1'b0; sel2 = 1'b1;
  #10 E6 = 1'b0; sel3 = 1'b1; sel0 = 1'b1; sel1 = 1'b1; sel2 = 1'b0;
  #10 E6 = 1'b1; sel3 = 1'b1; sel0 = 1'b1; sel1 = 1'b1; sel2 = 1'b0;
  #10 E7 = 1'b0; sel3 = 1'b1; sel0 = 1'b1; sel1 = 1'b1; sel2 = 1'b1;
  #10 E7 = 1'b1; sel3 = 1'b1; sel0 = 1'b1; sel1 = 1'b1; sel2 = 1'b1;
      
  #10 E8 = 1'b0; sel3 = 1'b0; sel0 = 1'b0; sel1 = 1'b0; sel2 = 1'b0;
  #10 E8 = 1'b1; sel3 = 1'b0; sel0 = 1'b0; sel1 = 1'b0; sel2 = 1'b0;
  #10 E9 = 1'b0; sel3 = 1'b0; sel0 = 1'b0; sel1 = 1'b0; sel2 = 1'b1;
  #10 E9 = 1'b1; sel3 = 1'b0; sel0 = 1'b0; sel1 = 1'b0; sel2 = 1'b1;
  #10 E10 = 1'b0; sel3 = 1'b0; sel0 = 1'b0; sel1 = 1'b1; sel2 = 1'b0;
  #10 E10 = 1'b1; sel3 = 1'b0; sel0 = 1'b0; sel1 = 1'b1; sel2 = 1'b0;
  #10 E11 = 1'b0; sel3 = 1'b0; sel0 = 1'b0; sel1 = 1'b1; sel2 = 1'b1;
  #10 E11 = 1'b1; sel3 = 1'b0; sel0 = 1'b0; sel1 = 1'b1; sel2 = 1'b1;
  #10 E12 = 1'b0; sel3 = 1'b0; sel0 = 1'b1; sel1 = 1'b0; sel2 = 1'b0;
  #10 E12 = 1'b1; sel3 = 1'b0; sel0 = 1'b1; sel1 = 1'b0; sel2 = 1'b0;
  #10 E13 = 1'b0; sel3 = 1'b0; sel0 = 1'b1; sel1 = 1'b0; sel2 = 1'b1;
  #10 E13 = 1'b1; sel3 = 1'b0; sel0 = 1'b1; sel1 = 1'b0; sel2 = 1'b1;
  #10 E14 = 1'b0; sel3 = 1'b0; sel0 = 1'b1; sel1 = 1'b1; sel2 = 1'b0;
  #10 E14 = 1'b1; sel3 = 1'b0; sel0 = 1'b1; sel1 = 1'b1; sel2 = 1'b0;
  #10 E15 = 1'b0; sel3 = 1'b0; sel0 = 1'b1; sel1 = 1'b1; sel2 = 1'b1;
  #10 E15 = 1'b1; sel3 = 1'b0; sel0 = 1'b1; sel1 = 1'b1; sel2 = 1'b1;
  #10; 
   end
  initial
    
    #310 $finish;

endmodule

16:1 Multiplexer/out.vcd
$date
	Fri Aug  4 04:17:30 2023
$end
$version
	Icarus Verilog
$end
$timescale
	100ps
$end
$scope module test_MULTI $end
$var wire 1 ! S $end
$var wire 1 " C2 $end
$var wire 1 # C1 $end
$var reg 1 $ E0 $end
$var reg 1 % E1 $end
$var reg 1 & E10 $end
$var reg 1 ' E11 $end
$var reg 1 ( E12 $end
$var reg 1 ) E13 $end
$var reg 1 * E14 $end
$var reg 1 + E15 $end
$var reg 1 , E2 $end
$var reg 1 - E3 $end
$var reg 1 . E4 $end
$var reg 1 / E5 $end
$var reg 1 0 E6 $end
$var reg 1 1 E7 $end
$var reg 1 2 E8 $end
$var reg 1 3 E9 $end
$var reg 1 4 sel0 $end
$var reg 1 5 sel1 $end
$var reg 1 6 sel2 $end
$var reg 1 7 sel3 $end
$upscope $end
$enddefinitions $end
#0
$dumpvars
x7
x6
x5
x4
x3
x2
x1
x0
x/
x.
x-
x,
x+
x*
x)
x(
x'
x&
x%
x$
x#
x"
x!
$end
#100
0!
0"
06
05
04
17
0$
#200
1!
1"
1$
#300
0!
0"
16
0%
#400
1!
1"
1%
#500
0!
0"
06
15
0,
#600
1!
1"
1,
#700
0!
0"
16
0-
#800
1!
1"
1-
#900
0!
0"
06
05
14
0.
#1000
1!
1"
1.
#1100
0!
0"
16
0/
#1200
1!
1"
1/
#1300
0!
0"
06
15
00
#1400
1!
1"
10
#1500
0!
0"
16
01
#1600
1!
1"
11
#1700
0!
0#
06
05
04
07
02
#1800
1!
1#
12
#1900
0!
0#
16
03
#2000
1!
1#
13
#2100
0!
0#
06
15
0&
#2200
1!
1#
1&
#2300
0!
0#
16
0'
#2400
1!
1#
1'
#2500
0!
0#
06
05
14
0(
#2600
1!
1#
1(
#2700
0!
0#
16
0)
#2800
1!
1#
1)
#2900
0!
0#
06
15
0*
#3000
1!
1#
1*
#3100
0!
0#
16
0+
