Mealey State Machine/design.sv
module mealy_state_machine (
  input wire clk, // Clock input
  input wire reset, // Reset input
  input wire in, // Input signal
  output reg state, // State output
  output reg out // Mealy output
);

  reg next_state;

  always @(posedge clk or posedge reset) begin
    if (reset) begin
      state <= 1'b0;
      out <= 1'b0;
    end else begin
      state <= next_state;
      out <= (state & in);
    end
  end

  always @(*) begin
    case (state)
      1'b0: next_state = in;
      1'b1: next_state = ~in;
      default: next_state = 1'b0;
    endcase
  end

endmodule

Mealey State Machine/testbench.sv
module testbench;

  reg clk;
  reg reset;
  reg in;
  wire state;
  wire out;

  mealy_state_machine uut (
    .clk(clk),
    .reset(reset),
    .in(in),
    .state(state),
    .out(out)
  );

  initial begin
    // Open VCD file for waveform dumping
    $dumpfile("waveform.vcd");
    $dumpvars(0, testbench); // Dump all variables
    
    // Initialize inputs
    clk = 0;
    reset = 0;
    in = 0;
    
    // Apply inputs and check outputs
    #5 reset = 1;
    #5 reset = 0;
    #10 clk = 1; #5 clk = 0; in = 1; // Transition from 0 to 1 (state 0)
    #10 clk = 1; #5 clk = 0; in = 0; // Transition from 1 to 0 (state 1)
    #10 clk = 1; #5 clk = 0; in = 1; // Transition from 0 to 1 (state 0)
    #10 clk = 1; #5 clk = 0; in = 0; // Transition from 1 to 0 (state 1)
    
    // Finish simulation
    $finish;
  end

endmodule

Mealey State Machine/waveform.vcd
$date
	Tue Sep 26 18:27:33 2023
$end
$version
	Icarus Verilog
$end
$timescale
	1s
$end
$scope module testbench $end
$var wire 1 ! out $end
$var wire 1 " state $end
$var reg 1 # clk $end
$var reg 1 $ in $end
$var reg 1 % reset $end
$scope module uut $end
$var wire 1 & clk $end
$var wire 1 ' in $end
$var wire 1 ( reset $end
$var reg 1 ) next_state $end
$var reg 1 * out $end
$var reg 1 + state $end
$upscope $end
$upscope $end
$enddefinitions $end
#0
$dumpvars
x+
x*
0)
0(
0'
0&
0%
0$
0#
x"
x!
$end
#5
0*
0!
0+
0"
1%
1(
#10
0%
0(
#20
1#
1&
#25
1)
1$
1'
0#
0&
#35
0)
1+
1"
1#
1&
#40
1)
0$
0'
0#
0&
#50
1#
1&
#55
0)
1$
1'
0#
0&
#65
1)
1*
1!
0+
0"
1#
1&
#70
0)
0$
0'
0#
0&
