Decade Counter/design.sv
module decade_counter (
  input wire clk, // Clock input
  input wire reset, // Reset input
  output reg [3:0] count // 4-bit counter output
);

  always @(posedge clk or posedge reset) begin
    if (reset) begin
      count <= 4'b0000;
    end else begin
      if (count == 4'b1001) begin
        count <= 4'b0000;
      end else begin
        count <= count + 1;
      end
    end
  end

endmodule

Decade Counter/testbench.sv
module testbench;

  reg clk;
  reg reset;
  wire [3:0] count;

  decade_counter uut (
    .clk(clk),
    .reset(reset),
    .count(count)
  );

  initial begin
    // Open VCD file for waveform dumping
    $dumpfile("waveform.vcd");
    $dumpvars(0, testbench); // Dump all variables
    
    // Initialize inputs
    clk = 0;
    reset = 0;
    
    // Apply inputs and check outputs
    #5 reset = 1;
    #5 reset = 0;
    #10 clk = 1; #5 clk = 0; // Increment counter (0 -> 1)
    #10 clk = 1; #5 clk = 0; // Increment counter (1 -> 2)
    #10 clk = 1; #5 clk = 0; // Increment counter (2 -> 3)
    #10 clk = 1; #5 clk = 0; // Increment counter (3 -> 4)
    #10 clk = 1; #5 clk = 0; // Increment counter (4 -> 5)
    #10 clk = 1; #5 clk = 0; // Increment counter (5 -> 6)
    #10 clk = 1; #5 clk = 0; // Increment counter (6 -> 7)
    #10 clk = 1; #5 clk = 0; // Increment counter (7 -> 8)
    #10 clk = 1; #5 clk = 0; // Increment counter (8 -> 9)
    #10 clk = 1; #5 clk = 0; // Increment counter (9 -> 0)
    
    // Finish simulation
    $finish;
  end

endmodule

Decade Counter/waveform.vcd
$date
	Thu Sep 28 16:11:59 2023
$end
$version
	Icarus Verilog
$end
$timescale
	1s
$end
$scope module testbench $end
$var wire 4 ! count [3:0] $end
$var reg 1 " clk $end
$var reg 1 # reset $end
$scope module uut $end
$var wire 1 $ clk $end
$var wire 1 % reset $end
$var reg 4 & count [3:0] $end
$upscope $end
$upscope $end
$enddefinitions $end
#0
$dumpvars
bx &
0%
0$
0#
0"
bx !
$end
#5
b0 &
b0 !
1#
1%
#10
0#
0%
#20
b1 &
b1 !
1"
1$
#25
0"
0$
#35
b10 &
b10 !
1"
1$
#40
0"
0$
#50
b11 &
b11 !
1"
1$
#55
0"
0$
#65
b100 &
b100 !
1"
1$
#70
0"
0$
#80
b101 &
b101 !
1"
1$
#85
0"
0$
#95
b110 &
b110 !
1"
1$
#100
0"
0$
#110
b111 &
b111 !
1"
1$
#115
0"
0$
#125
b1000 &
b1000 !
1"
1$
#130
0"
0$
#140
b1001 &
b1001 !
1"
1$
#145
0"
0$
#155
b0 &
b0 !
1"
1$
