7 Segment Display/design.sv
// Code your design here
//Verilog module.
module segment7(
     bcd,
     seg
    );
     
     
     input [3:0] bcd;
     output [6:0] seg;
     reg [6:0] seg;


    always @(bcd)
    begin
        case (bcd) 
            0 : seg = 7'b0000001;
            1 : seg = 7'b1001111;
            2 : seg = 7'b0010010;
            3 : seg = 7'b0000110;
            4 : seg = 7'b1001100;
            5 : seg = 7'b0100100;
            6 : seg = 7'b0100000;
            7 : seg = 7'b0001111;
            8 : seg = 7'b0000000;
            9 : seg = 7'b0000100;
            
            default : seg = 7'b1111111; 
        endcase
    end
    
endmodule

7 Segment Display/testbench.sv
// Code your testbench here
// or browse Examples
module tb_segment7;

    reg [3:0] bcd;
    wire [6:0] seg;
    integer i;

    // Instantiate the Unit Under Test (UUT)
    segment7 uut (
        .bcd(bcd), 
        .seg(seg));
    
  
  
  
 

//Apply inputs
    initial begin
        for(i = 0;i < 16;i = i+1) //run loop for 0 to 15.
        begin
          $dumpfile("dump.vcd");
          $dumpvars(1);
            bcd = i; 
            #10; //wait for 10 ns
        end     
    end
      
endmodule

7 Segment Display/dump.vcd
$date
Wed Aug  2 08:57:33 2023
$end
$version
Riviera-PRO Version 2022.04.117.8517
$end
$timescale
1 ns
$end

$scope module tb_segment7 $end
$var wire 7 ! seg [6:0] $end
$var reg 4 " bcd [3:0] $end
$var integer 32 # i $end
$upscope $end

$enddefinitions $end
$dumpvars
b1 !
b0 "
b0 #
$end
#10
b1 #
b1 "
b1001111 !
#20
b10 #
b10 "
b10010 !
#30
b11 #
b11 "
b110 !
#40
b100 #
b100 "
b1001100 !
#50
b101 #
b101 "
b100100 !
#60
b110 #
b110 "
b100000 !
#70
b111 #
b111 "
b1111 !
#80
b1000 #
b1000 "
b0 !
#90
b1001 #
b1001 "
b100 !
#100
b1010 #
b1010 "
b1111111 !
#110
b1011 #
b1011 "
#120
b1100 #
b1100 "
#130
b1101 #
b1101 "
#140
b1110 #
b1110 "
#150
b1111 #
b1111 "
#160
b10000 #
