8:1 Multiplexer/design.sv
// Code your design here
module mux(y,s,in);
output  y;
input [7:0] in;
input [2:0] s;
reg y;
always @(s)
begin
if(s==3'd0) y=in[0];
else if(s==3'd1) y=in[1];
else if(s==3'd2) y=in[2];
else if(s==3'd3) y=in[3];
else if(s==3'd4) y=in[4];
else if(s==3'd5) y=in[5];
else if(s==3'd6) y=in[6];
else  y=in[7];
end
endmodule

8:1 Multiplexer/testbench.sv
// Code your testbench here
// or browse Examples
module tb_mux();
reg [7:0]in;
reg [2:0]s;
wire y;
mux m1(y,s,in);
initial
begin
in=8'b10110110;
s[0]=1'b0;
s[1]=1'b0;
s[2]=1'b0;
end
  initial begin
    $dumpfile("dump.vcd");
    $dumpvars(1);
  end
always #40  s[2]=~s[2];
always #20  s[1]=~s[1];
always #10  s[0]=~s[0];
initial
begin
#200 $finish;
end
endmodule

8:1 Multiplexer/dump.vcd
$date
Thu Aug  3 12:35:46 2023
$end
$version
Riviera-PRO Version 2022.04.117.8517
$end
$timescale
1 ns
$end

$scope module tb_mux $end
$var wire 1 ! y $end
$var reg 8 " in [7:0] $end
$var reg 3 # s [2:0] $end
$upscope $end

$enddefinitions $end
$dumpvars
0!
b10110110 "
b0 #
$end
#10
b1 #
1!
#20
b10 #
#30
b11 #
0!
#40
b100 #
1!
#50
b101 #
#60
b110 #
0!
#70
b111 #
1!
#80
b0 #
0!
#90
b1 #
1!
#100
b10 #
#110
b11 #
0!
#120
b100 #
1!
#130
b101 #
#140
b110 #
0!
#150
b111 #
1!
#160
b0 #
0!
#170
b1 #
1!
#180
b10 #
#190
b11 #
0!
