4 bit PISO register/design.sv
module piso_register (
  input wire [3:0] parallel_in, // 4-bit parallel input
  input wire clock, // Clock input
  input wire shift, // Shift control input
  output reg serial_out // Serial output
);

  reg [3:0] shift_reg;

  always @(posedge clock) begin
    if (shift) begin
      shift_reg <= {shift_reg[2:0], parallel_in[0]};
    end
  end

  always @(posedge clock) begin
    if (shift) begin
      serial_out <= shift_reg[3];
    end
  end

endmodule

4 bit PISO register/testbench.sv
module tb_piso_register;

  reg [3:0] parallel_in;
  reg clock;
  reg shift;
  wire serial_out;

  piso_register uut (
    .parallel_in(parallel_in),
    .clock(clock),
    .shift(shift),
    .serial_out(serial_out)
  );

  initial begin
    // Open VCD file for waveform dumping
    $dumpfile("waveform.vcd");
    $dumpvars(0, tb_piso_register); // Dump all variables
    
    // Initialize inputs
    parallel_in = 4'b0000;
    clock = 0;
    shift = 0;
    
    // Apply inputs and check outputs
    #5 parallel_in = 4'b1010; // Set parallel_in
    #5 shift = 1; // Shift data
    #5 shift = 0;
    #5 shift = 1; // Shift data
    #5 shift = 0;
    #5 shift = 1; // Shift data
    
    // Clock toggling
    repeat (10) begin
      #5 clock = ~clock;
    end
    
    // Finish simulation
    $finish;
  end

endmodule

4 bit PISO register/waveform.vcd
$date
	Tue Oct 10 05:33:46 2023
$end
$version
	Icarus Verilog
$end
$timescale
	1s
$end
$scope module tb_piso_register $end
$var wire 1 ! serial_out $end
$var reg 1 " clock $end
$var reg 4 # parallel_in [3:0] $end
$var reg 1 $ shift $end
$scope module uut $end
$var wire 1 % clock $end
$var wire 4 & parallel_in [3:0] $end
$var wire 1 ' shift $end
$var reg 1 ( serial_out $end
$var reg 4 ) shift_reg [3:0] $end
$upscope $end
$upscope $end
$enddefinitions $end
#0
$dumpvars
bx )
x(
0'
b0 &
0%
0$
b0 #
0"
x!
$end
#5
b1010 #
b1010 &
#10
1$
1'
#15
0$
0'
#20
1$
1'
#25
0$
0'
#30
1$
1'
#35
bx0 )
1"
1%
#40
0"
0%
#45
bx00 )
1"
1%
#50
0"
0%
#55
bx000 )
1"
1%
#60
0"
0%
#65
b0 )
1"
1%
#70
0"
0%
#75
0(
0!
1"
1%
