SR Flip Flop/design.sv
// SR Flip-Flop Verilog Code
module sr_flip_flop (
    input wire S,    // Set input
    input wire R,    // Reset input
    input wire CLK,  // Clock input
    output reg Q,    // Output Q
    output reg Qn    // Output Q' (inverted Q)
);

    // Sequential logic for the SR flip-flop
    always @(posedge CLK or posedge S or posedge R) begin
        if (S) begin
            Q <= 1'b1;
            Qn <= 1'b0;
        end else if (R) begin
            Q <= 1'b0;
            Qn <= 1'b1;
        end else begin
            Q <= Q;
            Qn <= Qn;
        end
    end

endmodule

SR Flip Flop/testbench.sv
// Testbench for SR Flip-Flop
module tb_sr_flip_flop();

    // Inputs
    reg S_tb;       // Set input
    reg R_tb;       // Reset input
    reg CLK_tb;     // Clock input

    // Outputs
    wire Q_tb;      // Output Q
    wire Qn_tb;     // Output Q' (inverted Q)

    // Instantiate the SR flip-flop
    sr_flip_flop uut (
        .S(S_tb),
        .R(R_tb),
        .CLK(CLK_tb),
        .Q(Q_tb),
        .Qn(Qn_tb)
    );

    // Clock generation
    always begin
        CLK_tb = 1'b0;
        #5;  // Half clock period delay
        CLK_tb = 1'b1;
        #5;  // Half clock period delay
    end

    // Stimulus generation
    initial begin
      $dumpfile("dump.vcd");
      $dumpvars(1);
        // Initialize inputs
        S_tb = 0;
        R_tb = 0;

        // Apply inputs and observe outputs
        $display("Time  S  R  Q  Qn");
        $display("----  -  -  -  --");
        #10 S_tb = 1; R_tb = 0;  // Set the flip-flop
        #10 S_tb = 0; R_tb = 1;  // Reset the flip-flop
        #10 S_tb = 0; R_tb = 0;  // No change
        #10 S_tb = 1; R_tb = 1;  // Invalid state (set and reset at the same time)
        #10 S_tb = 0; R_tb = 0;  // No change
        #10 S_tb = 1; R_tb = 0;  // Set the flip-flop
        #10 S_tb = 0; R_tb = 1;  // Reset the flip-flop
        #10 S_tb = 0; R_tb = 0;  // No change

        // Finish simulation
        $finish;
    end

endmodule

SR Flip Flop/dump.vcd
$date
	Fri Sep  1 14:54:09 2023
$end
$version
	Icarus Verilog
$end
$timescale
	1s
$end
$scope module tb_sr_flip_flop $end
$var wire 1 ! Q_tb $end
$var wire 1 " Qn_tb $end
$var reg 1 # CLK_tb $end
$var reg 1 $ R_tb $end
$var reg 1 % S_tb $end
$upscope $end
$enddefinitions $end
#0
$dumpvars
0%
0$
0#
x"
x!
$end
#5
1#
#10
0"
1!
0#
1%
#15
1#
#20
1"
0!
0#
1$
0%
#25
1#
#30
0#
0$
#35
1#
#40
0"
1!
0#
1$
1%
#45
1#
#50
0#
0$
0%
#55
1#
#60
0#
1%
#65
1#
#70
1"
0!
0#
1$
0%
#75
1#
#80
0#
0$
