MOD 8 DOWN Counter/design.sv
module mod8_down_counter (
  input wire clk, // Clock input
  input wire reset, // Reset input
  output reg [2:0] count // 3-bit counter output
);

  always @(posedge clk or posedge reset) begin
    if (reset) begin
      count <= 3'b111;
    end else begin
      if (count == 3'b000) begin
        count <= 3'b111;
      end else begin
        count <= count - 1;
      end
    end
  end

endmodule

MOD 8 DOWN Counter/testbench.sv
module testbench;

  reg clk;
  reg reset;
  wire [2:0] count;

  mod8_down_counter uut (
    .clk(clk),
    .reset(reset),
    .count(count)
  );

  initial begin
    // Open VCD file for waveform dumping
    $dumpfile("waveform.vcd");
    $dumpvars(0, testbench); // Dump all variables
    
    // Initialize inputs
    clk = 0;
    reset = 0;
    
    // Apply inputs and check outputs
    #5 reset = 1;
    #5 reset = 0;
    #10 clk = 1; #5 clk = 0; // Decrement counter (7 -> 6)
    #10 clk = 1; #5 clk = 0; // Decrement counter (6 -> 5)
    #10 clk = 1; #5 clk = 0; // Decrement counter (5 -> 4)
    #10 clk = 1; #5 clk = 0; // Decrement counter (4 -> 3)
    #10 clk = 1; #5 clk = 0; // Decrement counter (3 -> 2)
    #10 clk = 1; #5 clk = 0; // Decrement counter (2 -> 1)
    #10 clk = 1; #5 clk = 0; // Decrement counter (1 -> 0)
    #10 clk = 1; #5 clk = 0; // Decrement counter (0 -> 7)
    
    // Finish simulation
    $finish;
  end

endmodule

MOD 8 DOWN Counter/waveform.vcd
$date
	Thu Sep 21 19:16:25 2023
$end
$version
	Icarus Verilog
$end
$timescale
	1s
$end
$scope module testbench $end
$var wire 3 ! count [2:0] $end
$var reg 1 " clk $end
$var reg 1 # reset $end
$scope module uut $end
$var wire 1 $ clk $end
$var wire 1 % reset $end
$var reg 3 & count [2:0] $end
$upscope $end
$upscope $end
$enddefinitions $end
#0
$dumpvars
bx &
0%
0$
0#
0"
bx !
$end
#5
b111 &
b111 !
1#
1%
#10
0#
0%
#20
b110 &
b110 !
1"
1$
#25
0"
0$
#35
b101 &
b101 !
1"
1$
#40
0"
0$
#50
b100 &
b100 !
1"
1$
#55
0"
0$
#65
b11 &
b11 !
1"
1$
#70
0"
0$
#80
b10 &
b10 !
1"
1$
#85
0"
0$
#95
b1 &
b1 !
1"
1$
#100
0"
0$
#110
b0 &
b0 !
1"
1$
#115
0"
0$
#125
b111 &
b111 !
1"
1$
